KENN2/__init__.py
KENN2/parsers.py
KENN2/layers/Kenn.py
KENN2/layers/RangeConstraint.py
KENN2/layers/RelationalKENN.py
KENN2/layers/__init__.py
KENN2/layers/relational/GroupBy.py
KENN2/layers/relational/Join.py
KENN2/layers/relational/__init__.py
KENN2/layers/residual/ClauseEnhancer.py
KENN2/layers/residual/KnowledgeEnhancer.py
KENN2/layers/residual/__init__.py
KENN2-0.5.dist-info/LICENSE
KENN2-0.5.dist-info/METADATA
KENN2-0.5.dist-info/WHEEL
KENN2-0.5.dist-info/top_level.txt
KENN2-0.5.dist-info/RECORD
