Metadata-Version: 2.1
Name: KENN2
Version: 0.5
Summary: Knowledge Enhanced Neural Networks
Home-page: https://github.com/DanieleAlessandro/KENN2
Author: Alessandro Daniele, Riccardo Mazzieri, Luciano Serafini
Author-email: daniele@fbk.eu, serafini@fbk.eu
License: UNKNOWN
Project-URL: Bug Tracker, https://github.com/DanieleAlessandro/KENN2/issues
Keywords: kenn,Statistical Relational Learning,Neural Symbolic Learning,Learning with logic
Platform: UNKNOWN
Classifier: Programming Language :: Python :: 3
Classifier: License :: OSI Approved :: BSD License
Classifier: Operating System :: OS Independent
Requires-Python: >=3.6
License-File: LICENSE
Requires-Dist: tensorflow
Requires-Dist: numpy
